{
    "version": "0.4",
    "title": "Global Kit Styles",
    "type": "section",
    "metadata": {
        "template_type": "global-styles",
        "include_in_zip": "1",
        "elementor_pro_required": null,
        "additional_template_information": [
            "These are the global theme styles configured through the Elementor Theme Styles area."
        ],
        "wp_page_template": "default"
    },
    "content": [],
    "page_settings": {
        "system_colors": [
            {
                "_id": "primary",
                "title": "Primary Title",
                "color": "#262626"
            },
            {
                "_id": "secondary",
                "title": "Primary Subtitle",
                "color": "#54595F"
            },
            {
                "_id": "text",
                "title": "Text",
                "color": "#555555"
            },
            {
                "_id": "accent",
                "title": "Accent Red",
                "color": "#DA0E2B"
            }
        ],
        "custom_colors": [
            {
                "_id": "cf5b500",
                "title": "Secondary Title",
                "color": "#FFFFFF"
            },
            {
                "_id": "210a774",
                "title": "Secondary Subtitle",
                "color": "#FFFFFF"
            },
            {
                "_id": "bbde6aa",
                "title": "Secondary Text",
                "color": "#AAAAAA"
            }
        ],
        "system_typography": [
            {
                "_id": "primary",
                "title": "Primary Title",
                "typography_typography": "custom",
                "typography_font_family": "Merriweather",
                "typography_font_weight": "700",
                "typography_font_size": {
                    "unit": "px",
                    "size": 40,
                    "sizes": []
                },
                "typography_line_height": {
                    "unit": "px",
                    "size": 56,
                    "sizes": []
                }
            },
            {
                "_id": "secondary",
                "title": "Primary Subtitle",
                "typography_typography": "custom",
                "typography_font_family": "Lato",
                "typography_font_weight": "400",
                "typography_font_size": {
                    "unit": "px",
                    "size": 14,
                    "sizes": []
                },
                "typography_letter_spacing": {
                    "unit": "px",
                    "size": 5,
                    "sizes": []
                },
                "typography_line_height": {
                    "unit": "px",
                    "size": 28,
                    "sizes": []
                }
            },
            {
                "_id": "text",
                "title": "Text",
                "typography_typography": "custom",
                "typography_font_family": "Lato",
                "typography_font_weight": "400",
                "typography_font_size": {
                    "unit": "px",
                    "size": 15,
                    "sizes": []
                },
                "typography_line_height": {
                    "unit": "px",
                    "size": 26,
                    "sizes": []
                }
            },
            {
                "_id": "accent",
                "title": "Accent",
                "typography_typography": "custom",
                "typography_font_family": "Lato",
                "typography_font_weight": "500"
            }
        ],
        "custom_typography": [
            {
                "_id": "ba68789",
                "title": "Secondary Title",
                "typography_typography": "custom",
                "typography_font_family": "Merriweather",
                "typography_font_size": {
                    "unit": "px",
                    "size": 20,
                    "sizes": []
                },
                "typography_font_weight": "400",
                "typography_line_height": {
                    "unit": "px",
                    "size": 36,
                    "sizes": []
                }
            }
        ],
        "default_generic_fonts": "Sans-serif",
        "site_name": "Rekamkit",
        "site_description": "A Modern Videographer Elementor Template Kit",
        "page_title_selector": "h1.entry-title",
        "activeItemIndex": 1,
        "body_color": "#555555",
        "body_typography_typography": "custom",
        "body_typography_font_family": "Lato",
        "body_typography_font_size": {
            "unit": "px",
            "size": 15,
            "sizes": []
        },
        "body_typography_font_weight": "400",
        "body_typography_line_height": {
            "unit": "px",
            "size": 26,
            "sizes": []
        },
        "link_normal_color": "#FFFFFF",
        "link_normal_typography_typography": "custom",
        "link_normal_typography_font_family": "Lato",
        "link_normal_typography_font_size": {
            "unit": "px",
            "size": 15,
            "sizes": []
        },
        "link_normal_typography_font_weight": "700",
        "link_normal_typography_line_height": {
            "unit": "px",
            "size": 26,
            "sizes": []
        },
        "link_hover_color": "#FFFFFF",
        "link_hover_typography_typography": "custom",
        "link_hover_typography_font_family": "Lato",
        "link_hover_typography_font_size": {
            "unit": "px",
            "size": 15,
            "sizes": []
        },
        "link_hover_typography_font_weight": "700",
        "link_hover_typography_line_height": {
            "unit": "px",
            "size": 26,
            "sizes": []
        },
        "h1_color": "#262626",
        "h1_typography_typography": "custom",
        "h1_typography_font_family": "Merriweather",
        "h1_typography_font_size": {
            "unit": "px",
            "size": 80,
            "sizes": []
        },
        "h1_typography_font_weight": "400",
        "h1_typography_line_height": {
            "unit": "px",
            "size": 100,
            "sizes": []
        },
        "h2_color": "#262626",
        "h2_typography_typography": "custom",
        "h2_typography_font_size": {
            "unit": "px",
            "size": 40,
            "sizes": []
        },
        "h2_typography_font_weight": "400",
        "h2_typography_line_height": {
            "unit": "px",
            "size": 56,
            "sizes": []
        },
        "h3_color": "#262626",
        "h3_typography_typography": "custom",
        "h3_typography_font_family": "Merriweather",
        "h3_typography_font_size": {
            "unit": "px",
            "size": 30,
            "sizes": []
        },
        "h3_typography_font_weight": "400",
        "h3_typography_line_height": {
            "unit": "px",
            "size": 46,
            "sizes": []
        },
        "h4_color": "#262626",
        "h4_typography_typography": "custom",
        "h4_typography_font_family": "Merriweather",
        "h4_typography_font_size": {
            "unit": "px",
            "size": 24,
            "sizes": []
        },
        "h4_typography_font_weight": "700",
        "h4_typography_line_height": {
            "unit": "px",
            "size": 40,
            "sizes": []
        },
        "h5_color": "#262626",
        "h5_typography_typography": "custom",
        "h5_typography_font_family": "Lato",
        "h5_typography_font_size": {
            "unit": "px",
            "size": 18,
            "sizes": []
        },
        "h5_typography_font_weight": "700",
        "h5_typography_line_height": {
            "unit": "px",
            "size": 32,
            "sizes": []
        },
        "h6_color": "#262626",
        "h6_typography_typography": "custom",
        "h6_typography_font_family": "Lato",
        "h6_typography_font_size": {
            "unit": "px",
            "size": 14,
            "sizes": []
        },
        "h6_typography_font_weight": "700",
        "h6_typography_line_height": {
            "unit": "px",
            "size": 30,
            "sizes": []
        },
        "h6_typography_letter_spacing": {
            "unit": "px",
            "size": 10,
            "sizes": []
        },
        "button_typography_typography": "custom",
        "button_typography_font_family": "Lato",
        "button_typography_font_size": {
            "unit": "px",
            "size": 13,
            "sizes": []
        },
        "button_typography_font_weight": "900",
        "button_typography_text_transform": "uppercase",
        "button_typography_line_height": {
            "unit": "px",
            "size": "",
            "sizes": []
        },
        "button_typography_letter_spacing": {
            "unit": "px",
            "size": 0.8,
            "sizes": []
        },
        "button_text_color": "#FFFFFF",
        "button_background_color": "#DA0E2B",
        "button_border_border": "solid",
        "button_border_width": {
            "unit": "px",
            "top": "2",
            "right": "2",
            "bottom": "2",
            "left": "2",
            "isLinked": true
        },
        "button_border_color": "#FFFFFF",
        "button_border_radius": {
            "unit": "px",
            "top": "0",
            "right": "0",
            "bottom": "0",
            "left": "0",
            "isLinked": true
        },
        "button_hover_text_color": "#FFFFFF",
        "button_hover_background_color": "#FFFFFF33",
        "button_hover_border_border": "solid",
        "button_hover_border_width": {
            "unit": "px",
            "top": "2",
            "right": "2",
            "bottom": "2",
            "left": "2",
            "isLinked": true
        },
        "button_hover_border_color": "#FFFFFF",
        "button_hover_border_radius": {
            "unit": "px",
            "top": "0",
            "right": "0",
            "bottom": "0",
            "left": "0",
            "isLinked": true
        },
        "__globals__": {
            "link_normal_color": "",
            "h1_color": "globals\/colors?id=primary",
            "h2_color": "globals\/colors?id=primary",
            "h3_color": "globals\/colors?id=primary",
            "h4_color": "globals\/colors?id=primary",
            "h5_color": "globals\/colors?id=primary",
            "h6_color": "globals\/colors?id=primary",
            "button_background_color": "globals\/colors?id=accent",
            "button_border_color": ""
        }
    }
}